dquack/__init__.py
dquack/cli/__init__.py
dquack/constant.py
dquack/core/__init__.py
dquack/core/constraint.py
dquack/core/contract.py
dquack/core/engine.py
dquack/exceptions.py
dquack/logger.py
dquack/validation.py
dquack-0.1.3.dist-info/METADATA
dquack-0.1.3.dist-info/WHEEL
dquack-0.1.3.dist-info/RECORD
