Metadata-Version: 2.1
Name: dquack
Version: 0.1.3
Summary: 
Author: Duc Nguyen
Author-email: me@vanducng.dev
Requires-Python: >=3.9,<4.0
Classifier: Programming Language :: Python :: 3
Classifier: Programming Language :: Python :: 3.9
Classifier: Programming Language :: Python :: 3.10
Classifier: Programming Language :: Python :: 3.11
Classifier: Programming Language :: Python :: 3.12
Requires-Dist: Jinja2 (>=3.1.0,<4.0.0)
Requires-Dist: chardet (>=5.2.0,<6.0.0)
Requires-Dist: duckdb (>=0.10.0,<0.11.0)
Requires-Dist: openpyxl (>=3.1.2,<4.0.0)
Requires-Dist: pandas (>=2.2.1,<3.0.0)
